{
  "title": "图片",
  "enable": true,
  "namespace": "mybricks.normal-pc.image",
  "author": "Mybricks",
  "author_name": "Mybricks",
  "version": "1.0.0",
  "description": "可预览的单图",
  "icon": "https://ali2.a.kwimgs.com/udata/pkg/ks-merchant/fangzhou/static_picture/image.0139bd109f4ecffa.svg",
  "data": "./data.json",
  "runtime": "./runtime.tsx",
  "editors": "./editors.tsx",
  "inputs": [
    {
      "id": "imgSrc",
      "title": "图片地址",
      "schema": {
        "type": "string"
      }
    },
    {
      "id": "slotProps",
      "title": "插槽参数",
      "schema": {
        "type": "string"
      }
    }
  ]
}