{
    "title": "JS计算",
    "visibility": true,
    "namespace": "mybricks.normal-pc.code.segment",
    "author": "Mybricks",
    "author_name": "Mybricks",
    "version": "1.0.0",
    "description": "JS计算",
    "icon": "https://ali2.a.kwimgs.com/udata/pkg/ks-merchant/fangzhou/static_picture/java-script.dd6d0de51f7fc441.svg",
    "editors": "./editors.ts",
    "runtime": "./runtime.ts",
    "rtType": "js-autorun",
    "inputs": [
        {
          "id": "input0",
          "title": "输入项0",
          "schema": {
            "type": "any"
          }
        }
      ],
    "outputs": [
        {
          "id": "output0",
          "title": "输出项0",
          "schema": {
            "type": "any"
          }
        }
    ]
}